<?xml version="1.0" encoding="utf-8"?>
<doctrine-mapping xmlns="http://doctrine-project.org/schemas/orm/doctrine-mapping" xmlns:xsi="http://www.w3.org/2001/XMLSchema-instance" xsi:schemaLocation="http://doctrine-project.org/schemas/orm/doctrine-mapping http://doctrine-project.org/schemas/orm/doctrine-mapping.xsd">
  <entity name="HopeChurch\GreaterBundle\Entity\Person" table="person"
	  repository-class="HopeChurch\GreaterBundle\Entity\PersonRepository">
    <id name="id" type="integer" column="id">
      <generator strategy="IDENTITY"/>
    </id>
    <field name="nameFirst" type="string" column="name_first" length="128"
	   nullable="false"/>
    <field name="nameLast" type="string" column="name_last" length="128"
	   nullable="true"/>
    <field name="notes" type="string" column="notes"
	   nullable="true"/>

    <many-to-one field="referrer" target-entity="Referrer"
		 join-column="referrer_id">
      <join-column name="referrer_id" referenced-column-name="id"/>
    </many-to-one>

    <field name="dateCreated" type="date" column="date_created"
	   nullable="false"/>
    <field name="email" type="string" column="email" length="256"
	   nullable="true"/>
    <field name="phoneCell" type="string" column="phone_cell" length="20"
	   nullable="true"/>
    <field name="phoneHome" type="string" column="phone_home" length="20"
	   nullable="true"/>
    <field name="addrFirst" type="string" column="addr_first" length="128"
	   nullable="true"/>
    <field name="addrSecond" type="string" column="addr_second" length="128"
	   nullable="true"/>
    <field name="addrCity" type="string" column="addr_city" length="128"
	   nullable="true"/>
    <field name="addrState" type="string" column="addr_state" length="128"
	   nullable="true"/>
    <field name="addrZip" type="string" column="addr_zip" length="128"
	   nullable="true"/>
    <field name="addrCountry" type="string" column="addr_country" length="128"
	   nullable="true"/>
    <field name="facebook" type="boolean" column="facebook" nullable="true"/>

    <many-to-one field="family" target-entity="Family" join-column="family"
		 inversed-by="people">
      <join-column name="family_id" referenced-column-name="id"/>
    </many-to-one>

    <many-to-one field="smallgroup" target-entity="Smallgroup"
		 join-column="smallgroup" inversed-by="people">
      <join-column name="smallgroup_id" referenced-column-name="id"/>
    </many-to-one>

    <many-to-one field="leader" target-entity="Person" join-column="leader_id">
      <join-column name="leader_id" referenced-column-name="id"/>
    </many-to-one>

    <one-to-many field="attended" target-entity="Attendance"
		 mapped-by="person"/>

    <many-to-many field="roles" target-entity="Role" inversed-by="people">
      <join-table name="person_role">
        <join-columns>
          <join-column id="person_id" referenced-column-name="id" />
        </join-columns>
        <inverse-join-columns>
          <join-column id="role_id" referenced-column-name="id" />
        </inverse-join-columns>
      </join-table>
    </many-to-many>

    <lifecycle-callbacks>
      <lifecycle-callback type="prePersist" method="setDateCreatedValue" />
    </lifecycle-callbacks>
  </entity>
</doctrine-mapping>
